pd_parser/__init__.py
pd_parser/parse_pd.py
pd_parser/commands/__init__.py
pd_parser/commands/run.py
pd_parser-0.8.dist-info/LICENSE
pd_parser-0.8.dist-info/METADATA
pd_parser-0.8.dist-info/WHEEL
pd_parser-0.8.dist-info/entry_points.txt
pd_parser-0.8.dist-info/top_level.txt
pd_parser-0.8.dist-info/RECORD
