Metadata-Version: 2.1
Name: pd-parser
Version: 0.8
Summary: pd-parser: Take a potentially corrupted photodiode channel and find the event time samples at which it turned on.
Home-page: https://github.com/alexrockhill/pd-parser/
Download-URL: https://github.com/alexrockhill/pd-parser.git
Maintainer: Alex Rockhill
Maintainer-email: aprockhill@mailbox.org
License: BSD (3-clause)
Project-URL: Bug Reports, https://github.com/alexrockhill/pd-parser/issues
Project-URL: Source, https://github.com/alexrockhill/pd-parser
Platform: any
Classifier: Intended Audience :: Science/Research
Classifier: Intended Audience :: Developers
Classifier: License :: OSI Approved
Classifier: Programming Language :: Python
Classifier: Topic :: Software Development
Classifier: Topic :: Scientific/Engineering
Classifier: Operating System :: Microsoft :: Windows
Classifier: Operating System :: POSIX
Classifier: Operating System :: Unix
Classifier: Operating System :: MacOS
Classifier: Programming Language :: Python :: 3.5
Classifier: Programming Language :: Python :: 3.6
Classifier: Programming Language :: Python :: 3.7
Requires-Python: ~=3.5
License-File: LICENSE
Requires-Dist: numpy (>=1.19.0)
Requires-Dist: mne (>=0.19.1)
Requires-Dist: mne-bids
Requires-Dist: scipy
Requires-Dist: pybv
Requires-Dist: matplotlib
Requires-Dist: argparse
Requires-Dist: tqdm
